mymongo/__init__.py
mymongo/document.py
mymongo/store.py
mymongo/utils.py
mymongo-0.1.0.dist-info/LICENSE
mymongo-0.1.0.dist-info/METADATA
mymongo-0.1.0.dist-info/WHEEL
mymongo-0.1.0.dist-info/RECORD
