Metadata-Version: 2.1
Name: mymongo
Version: 0.1.0
Summary: A Python package for effortless object-document mapping using pymongo and pydantic to interface with MongoDB.
Home-page: https://github.com/Ale-Cas/mymongo
Author: Alessio Castrica
Author-email: castricaalessio@gmail.com
Requires-Python: >=3.10,<4.0
Classifier: Programming Language :: Python :: 3
Classifier: Programming Language :: Python :: 3.10
Classifier: Programming Language :: Python :: 3.11
Classifier: Programming Language :: Python :: 3.12
Requires-Dist: pydantic (>=1.10.7)
Requires-Dist: pymongo (>=4.6.0,<5.0.0)
Requires-Dist: querytyper (>=0.1.0,<0.2.0)
Requires-Dist: ulid-py (>=1.1.0,<2.0.0)
Project-URL: Repository, https://github.com/Ale-Cas/mymongo
